{
  "date" : "2026-04-06",
  "waves" : [
    {
      "difficulty" : "green",
      "grid" : [
        [
          "E",
          "C",
          "E",
          "L",
          "Z"
        ],
        [
          "P",
          "O",
          "O",
          "E",
          "I"
        ],
        [
          "T",
          "C",
          "I",
          "Y",
          "D"
        ],
        [
          "I",
          "O",
          "R",
          "A",
          "Y"
        ],
        [
          "R",
          "A",
          "R",
          "I",
          "D"
        ]
      ],
      "targetWord" : "COOEED"
    },
    {
      "difficulty" : "amber",
      "grid" : [
        [
          "R",
          "I",
          "T",
          "I",
          "G"
        ],
        [
          "I",
          "D",
          "V",
          "H",
          "I"
        ],
        [
          "V",
          "U",
          "F",
          "E",
          "E"
        ],
        [
          "Z",
          "T",
          "T",
          "A",
          "N"
        ],
        [
          "E",
          "N",
          "T",
          "H",
          "S"
        ]
      ],
      "targetWord" : "ATTENT"
    },
    {
      "difficulty" : "red",
      "grid" : [
        [
          "Q",
          "S",
          "I",
          "D",
          "U"
        ],
        [
          "E",
          "A",
          "X",
          "U",
          "I"
        ],
        [
          "Q",
          "E",
          "P",
          "T",
          "Q"
        ],
        [
          "T",
          "V",
          "T",
          "T",
          "F"
        ],
        [
          "V",
          "G",
          "C",
          "L",
          "H"
        ]
      ],
      "targetWord" : "PUTTEE"
    },
    {
      "difficulty" : "green",
      "grid" : [
        [
          "N",
          "N",
          "E",
          "O",
          "F"
        ],
        [
          "O",
          "D",
          "I",
          "V",
          "S"
        ],
        [
          "H",
          "N",
          "V",
          "B",
          "S"
        ],
        [
          "N",
          "A",
          "C",
          "C",
          "I"
        ],
        [
          "O",
          "I",
          "R",
          "R",
          "R"
        ]
      ],
      "targetWord" : "ACNODE"
    },
    {
      "difficulty" : "amber",
      "grid" : [
        [
          "P",
          "E",
          "I",
          "F",
          "V"
        ],
        [
          "O",
          "G",
          "W",
          "W",
          "M"
        ],
        [
          "H",
          "B",
          "Y",
          "A",
          "W"
        ],
        [
          "U",
          "N",
          "N",
          "S",
          "B"
        ],
        [
          "R",
          "A",
          "N",
          "G",
          "O"
        ]
      ],
      "targetWord" : "AWEIGH"
    },
    {
      "difficulty" : "red",
      "grid" : [
        [
          "I",
          "U",
          "T",
          "O",
          "J"
        ],
        [
          "N",
          "G",
          "L",
          "Y",
          "Z"
        ],
        [
          "H",
          "A",
          "J",
          "R",
          "A"
        ],
        [
          "V",
          "G",
          "E",
          "R",
          "I"
        ],
        [
          "L",
          "E",
          "N",
          "E",
          "I"
        ]
      ],
      "targetWord" : "AERIER"
    }
  ]
}
